emailedbefore/__init__.py
emailedbefore/py.typed
emailedbefore/sent_emails.py
emailed_before-0.2.0.dist-info/LICENSE.txt
emailed_before-0.2.0.dist-info/METADATA
emailed_before-0.2.0.dist-info/WHEEL
emailed_before-0.2.0.dist-info/top_level.txt
emailed_before-0.2.0.dist-info/RECORD
