Metadata-Version: 2.1
Name: emailed-before
Version: 0.2.0
Summary: UNKNOWN
Home-page: UNKNOWN
License: UNKNOWN
Platform: UNKNOWN
Requires-Python: >=3.7
